kk598/p3.py
kk598-0.3.dist-info/METADATA
kk598-0.3.dist-info/WHEEL
kk598-0.3.dist-info/top_level.txt
kk598-0.3.dist-info/RECORD
