Metadata-Version: 2.1
Name: kk598
Version: 0.3
Summary: good mrng
Home-page: UNKNOWN
Author: Kamal Kumar
Author-email: kamalsir@ymail.com
License: UNKNOWN
Platform: UNKNOWN
Requires-Dist: kk595
Requires-Dist: kk596
